aliyunsdkantiddos_public/__init__.py
aliyunsdkantiddos_public/endpoint.py
aliyunsdkantiddos_public/request/__init__.py
aliyunsdkantiddos_public/request/v20170518/DescribeBgpPackByIpRequest.py
aliyunsdkantiddos_public/request/v20170518/DescribeCapRequest.py
aliyunsdkantiddos_public/request/v20170518/DescribeDdosCountRequest.py
aliyunsdkantiddos_public/request/v20170518/DescribeDdosCreditRequest.py
aliyunsdkantiddos_public/request/v20170518/DescribeDdosEventListRequest.py
aliyunsdkantiddos_public/request/v20170518/DescribeDdosThresholdRequest.py
aliyunsdkantiddos_public/request/v20170518/DescribeInstanceIpAddressRequest.py
aliyunsdkantiddos_public/request/v20170518/DescribeInstanceRequest.py
aliyunsdkantiddos_public/request/v20170518/DescribeIpDdosThresholdRequest.py
aliyunsdkantiddos_public/request/v20170518/DescribeIpLocationServiceRequest.py
aliyunsdkantiddos_public/request/v20170518/DescribeRegionsRequest.py
aliyunsdkantiddos_public/request/v20170518/ModifyDdosStatusRequest.py
aliyunsdkantiddos_public/request/v20170518/ModifyDefenseThresholdRequest.py
aliyunsdkantiddos_public/request/v20170518/ModifyIpDefenseThresholdRequest.py
aliyunsdkantiddos_public/request/v20170518/__init__.py
aliyun_python_sdk_antiddos_public-2.0.4.dist-info/LICENSE
aliyun_python_sdk_antiddos_public-2.0.4.dist-info/METADATA
aliyun_python_sdk_antiddos_public-2.0.4.dist-info/WHEEL
aliyun_python_sdk_antiddos_public-2.0.4.dist-info/top_level.txt
aliyun_python_sdk_antiddos_public-2.0.4.dist-info/RECORD
